pyihm/GUIs.py
pyihm/__init__.py
pyihm/__main__.py
pyihm/fit_mixture.py
pyihm/gen_param.py
pyihm/input_reading.py
pyihm/plots.py
pyihm/save_dict.py
pyihm/select_regions.py
pyihm/spectra_reading.py
pyihm-2.0.0.dist-info/LICENSE.txt
pyihm-2.0.0.dist-info/METADATA
pyihm-2.0.0.dist-info/WHEEL
pyihm-2.0.0.dist-info/top_level.txt
pyihm-2.0.0.dist-info/RECORD
