Metadata-Version: 2.1
Name: pyihm
Version: 2.0.0
Summary: Indirect Hard Modelling, in Python
Home-page: https://github.com/MetallerTM/pyihm
Author: Francesco Bruno, Letizia Fiorucci
Author-email: bruno@cerm.unifi.it
License: LICENSE.txt
Classifier: Programming Language :: Python :: 3
Classifier: Operating System :: OS Independent
Classifier: License :: OSI Approved :: BSD License
Requires-Python: >=3.10
License-File: LICENSE.txt
Requires-Dist: numpy
Requires-Dist: scipy
Requires-Dist: lmfit
Requires-Dist: seaborn
Requires-Dist: nmrglue
Requires-Dist: matplotlib >=3.7
Requires-Dist: csaps
Requires-Dist: klassez >=0.4a.6
